{"data":{"Year":[2017,2018,2022,2017,2018,2020,2022,2017,2018,2019,2020,2021,2022,2017,2018,2019,2022,2017,2018,2020,2022,2017,2018,2020,2022,2017,2018,2020,2022,2017,2018,2020,2022,2017,2018,2020,2022,2018,2020,2022],"COMMENT_OBS":["Proportion of population covered by core Social Protection programs","Proportion of population covered by core Social Protection programs","Proportion of population covered by core Social Protection programs","Number of members of Pension and occupational Hazards","Number of members of Pension and occupational Hazards","Number of members of Pension and occupational Hazards","Number of members of Pension and occupational Hazards","Number of population covered by Medical scheme","Number of population covered by Medical scheme","Number of population covered by Medical scheme","Number of population covered by Medical scheme","Number of population covered by Medical scheme","Number of population covered by Medical scheme","Proportion of population covered by Community-Based Health Insurance (Coverage rate)","Proportion of population covered by Community-Based Health Insurance (Coverage rate)","Proportion of population covered by Community-Based Health Insurance (Coverage rate)","Proportion of population covered by Community-Based Health Insurance (Coverage rate)","Proportion of population covered by Health insurance","Proportion of population covered by Health insurance","Proportion of population covered by Health insurance","Proportion of population covered by Health insurance","Proportion of population covered by Health insurance","Proportion of population covered by Health insurance","Proportion of population covered by Health insurance","Proportion of population covered by Health insurance","Proportion of population covered by Health insurance","Proportion of population covered by Health insurance","Proportion of population covered by Health insurance","Proportion of population covered by Health insurance","Proportion of population covered by Health insurance","Proportion of population covered by Health insurance","Proportion of population covered by Health insurance","Proportion of population covered by Health insurance","Proportion of population covered by Health insurance","Proportion of population covered by Health insurance","Proportion of population covered by Health insurance","Proportion of population covered by Health insurance","Number of actively contributing women covered by Maternity Leave Benefits","Number of actively contributing women covered by Maternity Leave Benefits","Number of actively contributing women covered by Maternity Leave Benefits"],"Series":["Proportion of population covered by core Social Protection programs","Proportion of population covered by core Social Protection programs","Proportion of population covered by core Social Protection programs","Number of members of Pension and occupational Hazards","Number of members of Pension and occupational Hazards","Number of members of Pension and occupational Hazards","Number of members of Pension and occupational Hazards","Number of population covered by Medical scheme","Number of population covered by Medical scheme","Number of population covered by Medical scheme","Number of population covered by Medical scheme","Number of population covered by Medical scheme","Number of population covered by Medical scheme","Proportion of population covered by Community-Based Health Insurance (Coverage rate)","Proportion of population covered by Community-Based Health Insurance (Coverage rate)","Proportion of population covered by Community-Based Health Insurance (Coverage rate)","Proportion of population covered by Community-Based Health Insurance (Coverage rate)","Proportion of population covered by Health insurance","Proportion of population covered by Health insurance","Proportion of population covered by Health insurance","Proportion of population covered by Health insurance","Proportion of population covered by Health insurance","Proportion of population covered by Health insurance","Proportion of population covered by Health insurance","Proportion of population covered by Health insurance","Proportion of population covered by Health insurance","Proportion of population covered by Health insurance","Proportion of population covered by Health insurance","Proportion of population covered by Health insurance","Proportion of population covered by Health insurance","Proportion of population covered by Health insurance","Proportion of population covered by Health insurance","Proportion of population covered by Health insurance","Proportion of population covered by Health insurance","Proportion of population covered by Health insurance","Proportion of population covered by Health insurance","Proportion of population covered by Health insurance","Number of actively contributing women covered by Maternity Leave Benefits","Number of actively contributing women covered by Maternity Leave Benefits","Number of actively contributing women covered by Maternity Leave Benefits"],"Sex":[null,null,null,null,null,null,null,null,null,null,null,null,null,null,null,null,null,null,null,null,null,null,null,null,null,null,null,null,null,"Male","Male","Male","Male","Female","Female","Female","Female",null,null,null],"Degree of urbanisation":[null,null,null,null,null,null,null,null,null,null,null,null,null,null,null,null,null,null,null,null,null,"Urban","Urban","Urban","Urban","Rural","Rural","Rural","Rural",null,null,null,null,null,null,null,null,null,null,null],"Units":["Percent","Percent","Percent","Number","Number","Number","Number","Number","Number","Number","Number","Number","Number","Percent","Percent","Percent","Percent","Percent","Percent","Percent","Percent","Percent","Percent","Percent","Percent","Percent","Percent","Percent","Percent","Percent","Percent","Percent","Percent","Percent","Percent","Percent","Percent","Number","Number","Number"],"Value":[6.5,6.5,11.0,484435.0,560769.0,610263.0,705713.0,376836.0,432450.0,532297.0,579623.0,554048.0,608436.0,84.2,83.3,80.0,93.0,70.0,73.9,86.0,97.3,73.8,79.5,87.2,96.7,69.2,72.7,85.6,97.5,69.4,73.4,83.0,97.1,70.5,74.5,83.3,97.5,164601.0,227152.0,233982.0]},"edges":{"From":["COMMENT_OBS","COMMENT_OBS"],"To":["Sex","Degree of urbanisation"]}}