{"Year":[2012,2022],"COMMENT_OBS":["The proportion of heavy drinkers (\u226560g of pure alcohol/ six standard drinks on average per\noccasion among men and \u226540g of pure alcohol4 standard drinks on average per occasion among\nwomen).","The proportion of heavy drinkers (\u226560g of pure alcohol/ six standard drinks on average per\noccasion among men and \u226540g of pure alcohol4 standard drinks on average per occasion among\nwomen)."],"SOURCE_DETAIL":["MoH, Steps Survey","MoH, Steps Survey"],"SERIES":["SH_ALC_CONSPT","SH_ALC_CONSPT"],"REF_AREA":[null,null],"UNIT_MEASURE":["PT","PT"],"GeoCode":[null,null],"Value":[23.5,15.2]}